[{"h3_12_4M":"8c5809706a805ff","lat":13.0309413,"lon":10.3286685,"hours":null,"location_details":null,"address":null,"url":null,"type":null,"city2":"Nguru","state2":"Yobe State","country2":"Nigeria"},{"h3_12_4M":"8c580a44242edff","lat":12.0535302,"lon":8.5831207,"hours":null,"location_details":null,"address":null,"url":null,"type":null,"city2":"Kano","state2":"Kano State","country2":"Nigeria"},{"h3_12_4M":"8c580a4502751ff","lat":12.0372209,"lon":8.5673469,"hours":null,"location_details":null,"address":null,"url":null,"type":null,"city2":"Kano","state2":"Kano State","country2":"Nigeria"},{"h3_12_4M":"8c580a4f0464bff","lat":11.9590563,"lon":8.4707437,"hours":null,"location_details":null,"address":null,"url":null,"type":null,"city2":"Kano","state2":"Kano State","country2":"Nigeria"},{"h3_12_4M":"8c580a4f05493ff","lat":11.9595406,"lon":8.4712034,"hours":null,"location_details":null,"address":null,"url":null,"type":null,"city2":"Kano","state2":"Kano State","country2":"Nigeria"},{"h3_12_4M":"8c580a4f055edff","lat":11.9589365,"lon":8.4691957,"hours":null,"location_details":null,"address":null,"url":null,"type":null,"city2":"Kano","state2":"Kano State","country2":"Nigeria"},{"h3_12_4M":"8c580e16e4061ff","lat":13.4196321,"lon":8.1795033,"hours":null,"location_details":null,"address":null,"url":null,"type":null,"city2":"Mai’Adua","state2":"Katsina State","country2":"Nigeria"},{"h3_12_4M":"8c580e16e4063ff","lat":13.4196173,"lon":8.1795948,"hours":null,"location_details":null,"address":null,"url":null,"type":null,"city2":"Mai’Adua","state2":"Katsina State","country2":"Nigeria"},{"h3_12_4M":"8c5853a6409b7ff","lat":11.7883722,"lon":13.130154233333334,"hours":null,"location_details":null,"address":null,"url":null,"type":null,"city2":"Maiduguri","state2":"Borno State","country2":"Nigeria"},{"h3_12_4M":"8c5853a640c09ff","lat":11.7902007,"lon":13.1327622,"hours":null,"location_details":null,"address":null,"url":null,"type":null,"city2":"Maiduguri","state2":"Borno State","country2":"Nigeria"},{"h3_12_4M":"8c5853a640ce7ff","lat":11.7894835,"lon":13.1335112,"hours":null,"location_details":null,"address":null,"url":null,"type":null,"city2":"Maiduguri","state2":"Borno State","country2":"Nigeria"},{"h3_12_4M":"8c5853a640dd3ff","lat":11.7892687,"lon":13.1334971,"hours":null,"location_details":null,"address":null,"url":null,"type":null,"city2":"Maiduguri","state2":"Borno State","country2":"Nigeria"},{"h3_12_4M":"8c5853a640ee7ff","lat":11.7907006,"lon":13.1332098,"hours":null,"location_details":null,"address":null,"url":null,"type":null,"city2":"Maiduguri","state2":"Borno State","country2":"Nigeria"},{"h3_12_4M":"8c5853a64726bff","lat":11.7886503,"lon":13.1305888,"hours":null,"location_details":null,"address":null,"url":null,"type":null,"city2":"Maiduguri","state2":"Borno State","country2":"Nigeria"},{"h3_12_4M":"8c5853a647305ff","lat":11.787648,"lon":13.129952,"hours":null,"location_details":null,"address":null,"url":null,"type":null,"city2":"Maiduguri","state2":"Borno State","country2":"Nigeria"},{"h3_12_4M":"8c5853a647363ff","lat":11.7877052,"lon":13.1297007,"hours":null,"location_details":null,"address":null,"url":null,"type":null,"city2":"Maiduguri","state2":"Borno State","country2":"Nigeria"},{"h3_12_4M":"8c5853a64736bff","lat":11.7878713,"lon":13.1297979,"hours":null,"location_details":null,"address":null,"url":null,"type":null,"city2":"Maiduguri","state2":"Borno State","country2":"Nigeria"},{"h3_12_4M":"8c58550b6d311ff","lat":13.2078002,"lon":12.4246096,"hours":null,"location_details":null,"address":null,"url":null,"type":null,"city2":"Damasak","state2":"Borno State","country2":"Nigeria"},{"h3_12_4M":"8c58550b6da91ff","lat":13.2055044,"lon":12.4251108,"hours":null,"location_details":null,"address":null,"url":null,"type":null,"city2":"Damasak","state2":"Borno State","country2":"Nigeria"},{"h3_12_4M":"8c588265d35cdff","lat":6.5895759,"lon":3.3433816,"hours":null,"location_details":null,"address":null,"url":null,"type":null,"city2":"Ikeja","state2":"Lagos","country2":"Nigeria"},{"h3_12_4M":"8c58826c4d61dff","lat":6.5276684,"lon":3.2365016,"hours":null,"location_details":null,"address":null,"url":null,"type":null,"city2":"Ikotun","state2":"Lagos","country2":"Nigeria"},{"h3_12_4M":"8c588383140e9ff","lat":7.3604324,"lon":3.889251,"hours":null,"location_details":null,"address":null,"url":null,"type":null,"city2":"Ibadan","state2":"Oyo State","country2":"Nigeria"},{"h3_12_4M":"8c58838359017ff","lat":7.3924934,"lon":3.8775802,"hours":null,"location_details":null,"address":null,"url":null,"type":"pitlatrine","city2":"Ibadan","state2":"Oyo State","country2":"Nigeria"},{"h3_12_4M":"8c588e0088229ff","lat":6.9825039,"lon":5.1026993,"hours":null,"location_details":null,"address":null,"url":null,"type":null,"city2":"Idanre","state2":"Ondo State","country2":"Nigeria"},{"h3_12_4M":"8c588eba09107ff","lat":7.2956004,"lon":5.1465592,"hours":null,"location_details":null,"address":null,"url":null,"type":"flush","city2":"Akure","state2":"Ondo State","country2":"Nigeria"},{"h3_12_4M":"8c588eba41a25ff","lat":7.3043586,"lon":5.1355049,"hours":"24/7","location_details":null,"address":null,"url":null,"type":"flush","city2":"Ilare","state2":"Ondo State","country2":"Nigeria"},{"h3_12_4M":"8c588ebad2c0bff","lat":7.2818948,"lon":5.22336,"hours":null,"location_details":null,"address":null,"url":null,"type":"flush","city2":"Akure","state2":"Ondo State","country2":"Nigeria"},{"h3_12_4M":"8c589c912b803ff","lat":6.5782518,"lon":3.4101053,"hours":null,"location_details":null,"address":null,"url":null,"type":null,"city2":"Ojota","state2":"Lagos","country2":"Nigeria"},{"h3_12_4M":"8c589c924512bff","lat":6.6894907,"lon":3.4144028,"hours":null,"location_details":"Ogun state ministry of environment public toilets, Warewa","address":null,"url":null,"type":null,"city2":"Ifako","state2":"Lagos","country2":"Nigeria"},{"h3_12_4M":"8c58a319162abff","lat":9.4975132,"lon":3.0467179,"hours":null,"location_details":null,"address":null,"url":null,"type":null,"city2":"Suya","state2":"Kwara State","country2":"Nigeria"},{"h3_12_4M":"8c58a3ccb873dff","lat":9.5107382,"lon":2.9810098,"hours":null,"location_details":null,"address":null,"url":null,"type":null,"city2":"Suya","state2":"Kwara State","country2":"Nigeria"},{"h3_12_4M":"8c58e04606cd1ff","lat":10.3141386,"lon":9.8302214,"hours":null,"location_details":"Public rest room. Swimming pool project.","address":null,"url":null,"type":null,"city2":"Bauchi","state2":"Bauchi","country2":"Nigeria"},{"h3_12_4M":"8c58e172925e9ff","lat":10.3072336,"lon":11.1672112,"hours":"24/7","location_details":null,"address":null,"url":null,"type":null,"city2":"Gombe","state2":"Gombe State","country2":"Nigeria"},{"h3_12_4M":"8c58e172928a3ff","lat":10.3046573,"lon":11.1639193,"hours":"24/7","location_details":null,"address":null,"url":null,"type":null,"city2":"Gombe","state2":"Gombe State","country2":"Nigeria"},{"h3_12_4M":"8c58e17747905ff","lat":10.30202925,"lon":11.17644545,"hours":"24/7","location_details":null,"address":null,"url":null,"type":null,"city2":"Gombe","state2":"Gombe State","country2":"Nigeria"},{"h3_12_4M":"8c58e17747b61ff","lat":10.3032646,"lon":11.1757375,"hours":null,"location_details":null,"address":null,"url":null,"type":null,"city2":"Gombe","state2":"Gombe State","country2":"Nigeria"},{"h3_12_4M":"8c58e17768699ff","lat":10.3011539,"lon":11.170898,"hours":null,"location_details":null,"address":null,"url":null,"type":null,"city2":"Gombe","state2":"Gombe State","country2":"Nigeria"},{"h3_12_4M":"8c58ee0b12c51ff","lat":9.5121112,"lon":11.5859091,"hours":null,"location_details":null,"address":null,"url":null,"type":null,"city2":"Dadiya","state2":"Gombe State","country2":"Nigeria"},{"h3_12_4M":"8c58f0d1651abff","lat":8.9395584,"lon":7.4297518,"hours":null,"location_details":null,"address":null,"url":null,"type":null,"city2":"Abuja","state2":"FCT","country2":"Nigeria"},{"h3_12_4M":"8c58f0d165429ff","lat":8.9407674,"lon":7.4323723,"hours":null,"location_details":null,"address":null,"url":null,"type":null,"city2":"Abuja","state2":"FCT","country2":"Nigeria"},{"h3_12_4M":"8c58f0d34c86dff","lat":9.0153764,"lon":7.4201034,"hours":null,"location_details":null,"address":null,"url":null,"type":null,"city2":"Abuja","state2":"FCT","country2":"Nigeria"},{"h3_12_4M":"8c58f0d34c8ebff","lat":9.0150891,"lon":7.4215432,"hours":null,"location_details":null,"address":null,"url":null,"type":null,"city2":"Abuja","state2":"FCT","country2":"Nigeria"},{"h3_12_4M":"8c58f0d34c9cbff","lat":9.0146897,"lon":7.4209393,"hours":null,"location_details":null,"address":null,"url":null,"type":null,"city2":"Abuja","state2":"FCT","country2":"Nigeria"},{"h3_12_4M":"8c58f0d362b23ff","lat":8.9921308,"lon":7.4264622,"hours":null,"location_details":null,"address":null,"url":null,"type":null,"city2":"Abuja","state2":"FCT","country2":"Nigeria"},{"h3_12_4M":"8c58f1719b121ff","lat":8.4348711,"lon":9.099563,"hours":null,"location_details":null,"address":null,"url":null,"type":null,"city2":"Obi","state2":"Nasarawa State","country2":"Nigeria"},{"h3_12_4M":"8c58f1cdc7223ff","lat":8.6931915,"lon":8.7369175,"hours":null,"location_details":null,"address":null,"url":null,"type":null,"city2":"Nasarawa Egon","state2":"Nasarawa State","country2":"Nigeria"},{"h3_12_4M":"8c58f26de8469ff","lat":7.3159182,"lon":7.7239613,"hours":null,"location_details":null,"address":null,"url":null,"type":null,"city2":"Ankpa","state2":"Kogi State","country2":"Nigeria"},{"h3_12_4M":"8c58f26de8501ff","lat":7.3150983,"lon":7.7237321,"hours":null,"location_details":null,"address":null,"url":null,"type":null,"city2":"Ankpa","state2":"Kogi State","country2":"Nigeria"},{"h3_12_4M":"8c58f26de8503ff","lat":7.3150588,"lon":7.7238404,"hours":null,"location_details":null,"address":null,"url":null,"type":null,"city2":"Ankpa","state2":"Kogi State","country2":"Nigeria"},{"h3_12_4M":"8c58f26de85b1ff","lat":7.3143469,"lon":7.7251497,"hours":null,"location_details":null,"address":null,"url":null,"type":null,"city2":"Ankpa","state2":"Kogi State","country2":"Nigeria"},{"h3_12_4M":"8c58f26de86abff","lat":7.3162834,"lon":7.7252369,"hours":null,"location_details":null,"address":null,"url":null,"type":null,"city2":"Ankpa","state2":"Kogi State","country2":"Nigeria"},{"h3_12_4M":"8c58f3da92ed1ff","lat":8.0122267,"lon":8.1166855,"hours":null,"location_details":null,"address":null,"url":null,"type":null,"city2":"Obagaji","state2":"Benue State","country2":"Nigeria"},{"h3_12_4M":"8c58f5572628bff","lat":9.4832106,"lon":8.1470984,"hours":null,"location_details":null,"address":null,"url":null,"type":null,"city2":"Kwoi","state2":"Kaduna State","country2":"Nigeria"}]