[{"h3_12_4M":"8c21804858819ff","lat":41.2932454,"lon":61.5513928,"hours":null,"location_details":null,"address":null,"url":null,"type":null,"city2":"Gazojak","state2":"Lebap","country2":"Turkmenistan"},{"h3_12_4M":"8c2182a026151ff","lat":41.0872648,"lon":61.9683136,"hours":null,"location_details":null,"address":null,"url":null,"type":null,"city2":"Gazojak","state2":"Lebap","country2":"Turkmenistan"},{"h3_12_4M":"8c2182a026911ff","lat":41.083612,"lon":61.9692654,"hours":null,"location_details":null,"address":null,"url":null,"type":null,"city2":"Gazojak","state2":"Lebap","country2":"Turkmenistan"},{"h3_12_4M":"8c2182a1130a5ff","lat":41.0741092,"lon":61.9716926,"hours":null,"location_details":null,"address":null,"url":null,"type":"flush","city2":"Gazojak","state2":"Lebap","country2":"Turkmenistan"},{"h3_12_4M":"8c219251c56d3ff","lat":37.3720378,"lon":60.5193718,"hours":null,"location_details":null,"address":null,"url":null,"type":null,"city2":"Tejen","state2":"Ahal","country2":"Turkmenistan"},{"h3_12_4M":"8c2194d1512ebff","lat":39.3110544,"lon":58.5866963,"hours":null,"location_details":null,"address":null,"url":null,"type":null,"city2":"Babarap","state2":"Ahal","country2":"Turkmenistan"},{"h3_12_4M":"8c219e306b5a9ff","lat":39.1831289,"lon":63.5934912,"hours":"24/7","location_details":null,"address":null,"url":null,"type":null,"city2":"Farap","state2":"Lebap","country2":"Turkmenistan"},{"h3_12_4M":"8c219e308a1b1ff","lat":39.2065402,"lon":63.6987812,"hours":null,"location_details":null,"address":null,"url":null,"type":null,"city2":"Farap","state2":"Lebap","country2":"Turkmenistan"},{"h3_12_4M":"8c219e3861063ff","lat":39.0086886,"lon":63.5958486,"hours":null,"location_details":null,"address":null,"url":null,"type":null,"city2":"Türkmenabat","state2":"Lebap","country2":"Turkmenistan"},{"h3_12_4M":"8c219e3a1db47ff","lat":39.0740317,"lon":63.578722,"hours":null,"location_details":null,"address":null,"url":null,"type":null,"city2":"Türkmenabat","state2":"Lebap","country2":"Turkmenistan"},{"h3_12_4M":"8c219e3a5b459ff","lat":39.1015599,"lon":63.5712455,"hours":null,"location_details":null,"address":null,"url":null,"type":null,"city2":"Türkmenabat","state2":"Lebap","country2":"Turkmenistan"},{"h3_12_4M":"8c21b188d22b5ff","lat":41.8787252,"lon":58.7059438,"hours":null,"location_details":null,"address":null,"url":null,"type":null,"city2":"Köneürgench","state2":"Daşoguz","country2":"Turkmenistan"},{"h3_12_4M":"8c21b1b6a85adff","lat":42.332189,"lon":59.1469808,"hours":null,"location_details":null,"address":null,"url":null,"type":null,"city2":"Köneürgench","state2":"Daşoguz","country2":"Turkmenistan"},{"h3_12_4M":"8c21b1c690d3bff","lat":41.7411369,"lon":58.6903849,"hours":null,"location_details":"Four primitive outhouses. Bring your own paper and moist towelettes.","address":null,"url":null,"type":"pitlatrine","city2":"Köneürgench","state2":"Daşoguz","country2":"Turkmenistan"},{"h3_12_4M":"8c21b23647b2bff","lat":40.2069532,"lon":58.4064749,"hours":null,"location_details":null,"address":null,"url":null,"type":"pitlatrine","city2":"Baharly","state2":"Ahal","country2":"Turkmenistan"},{"h3_12_4M":"8c2cc82620b63ff","lat":38.3029623,"lon":57.6264721,"hours":null,"location_details":null,"address":null,"url":null,"type":null,"city2":"Baharly","state2":"Ahal","country2":"Turkmenistan"},{"h3_12_4M":"8c2cc83419b31ff","lat":38.3715323,"lon":57.5024616,"hours":null,"location_details":null,"address":null,"url":null,"type":null,"city2":"Baharly","state2":"Ahal","country2":"Turkmenistan"},{"h3_12_4M":"8c2cc89253437ff","lat":38.4949447,"lon":56.3483708,"hours":null,"location_details":null,"address":null,"url":null,"type":null,"city2":"Magtymguly","state2":"Balkan","country2":"Turkmenistan"},{"h3_12_4M":"8c2cc8a350dd5ff","lat":38.4900154,"lon":57.0363075,"hours":null,"location_details":null,"address":null,"url":null,"type":null,"city2":"Baharly","state2":"Ahal","country2":"Turkmenistan"},{"h3_12_4M":"8c2cc95b570a9ff","lat":38.2215121,"lon":57.8005065,"hours":null,"location_details":null,"address":null,"url":null,"type":"pitlatrine","city2":"Gökdepe","state2":"Ahal","country2":"Turkmenistan"},{"h3_12_4M":"8c2ccb009d311ff","lat":37.6287346,"lon":58.4070938,"hours":null,"location_details":null,"address":null,"url":null,"type":null,"city2":"Änew","state2":"Ahal","country2":"Turkmenistan"},{"h3_12_4M":"8c2ccb00d68b1ff","lat":37.6303328,"lon":58.4063166,"hours":null,"location_details":null,"address":null,"url":null,"type":null,"city2":"Änew","state2":"Ahal","country2":"Turkmenistan"},{"h3_12_4M":"8c2ccba04d415ff","lat":38.0280397,"lon":58.404784,"hours":null,"location_details":null,"address":null,"url":null,"type":null,"city2":"Ashgabat","state2":"Ashgabat","country2":"Turkmenistan"},{"h3_12_4M":"8c2ccba161a6dff","lat":37.942721,"lon":58.3966978,"hours":null,"location_details":null,"address":null,"url":null,"type":null,"city2":"Ashgabat","state2":"Ashgabat","country2":"Turkmenistan"},{"h3_12_4M":"8c2ccba16cb09ff","lat":37.9381128,"lon":58.3901993,"hours":null,"location_details":null,"address":null,"url":null,"type":null,"city2":"Ashgabat","state2":"Ashgabat","country2":"Turkmenistan"},{"h3_12_4M":"8c2ccba596889ff","lat":38.0728009,"lon":58.6999922,"hours":null,"location_details":null,"address":null,"url":null,"type":"flush","city2":"Änew","state2":"Ahal","country2":"Turkmenistan"},{"h3_12_4M":"8c2ccba596e23ff","lat":38.0745763,"lon":58.7010983,"hours":null,"location_details":null,"address":null,"url":null,"type":"flush","city2":"Änew","state2":"Ahal","country2":"Turkmenistan"},{"h3_12_4M":"8c2ccbaa0826dff","lat":37.9044496,"lon":58.3986943,"hours":null,"location_details":null,"address":null,"url":null,"type":null,"city2":"Ashgabat","state2":"Ashgabat","country2":"Turkmenistan"},{"h3_12_4M":"8c2ccbaa0d231ff","lat":37.8973687,"lon":58.3937096,"hours":null,"location_details":null,"address":null,"url":null,"type":null,"city2":"Ashgabat","state2":"Ashgabat","country2":"Turkmenistan"},{"h3_12_4M":"8c2ccbaa100bdff","lat":37.9112191,"lon":58.4341954,"hours":null,"location_details":null,"address":null,"url":null,"type":null,"city2":"Ashgabat","state2":"Ashgabat","country2":"Turkmenistan"},{"h3_12_4M":"8c2ccbaa1b123ff","lat":37.9194491,"lon":58.4308132,"hours":null,"location_details":null,"address":null,"url":null,"type":null,"city2":"Ashgabat","state2":"Ashgabat","country2":"Turkmenistan"},{"h3_12_4M":"8c2ccbaa1b147ff","lat":37.9200054,"lon":58.4303395,"hours":null,"location_details":null,"address":null,"url":null,"type":null,"city2":"Ashgabat","state2":"Ashgabat","country2":"Turkmenistan"},{"h3_12_4M":"8c2ccbaa359ebff","lat":37.8766013,"lon":58.4308274,"hours":null,"location_details":null,"address":null,"url":null,"type":"flush","city2":"Änew","state2":"Ahal","country2":"Turkmenistan"},{"h3_12_4M":"8c2ccbaa4735bff","lat":37.90308,"lon":58.3845964,"hours":null,"location_details":null,"address":null,"url":null,"type":"flush","city2":"Ashgabat","state2":"Ashgabat","country2":"Turkmenistan"},{"h3_12_4M":"8c2ccbaa59b59ff","lat":37.9252972,"lon":58.3920302,"hours":null,"location_details":null,"address":null,"url":null,"type":null,"city2":"Ashgabat","state2":"Ashgabat","country2":"Turkmenistan"},{"h3_12_4M":"8c2ccbb8ba2ddff","lat":37.9408805,"lon":58.380685,"hours":null,"location_details":null,"address":null,"url":null,"type":null,"city2":"Ashgabat","state2":"Ashgabat","country2":"Turkmenistan"},{"h3_12_4M":"8c2ccc2842293ff","lat":38.5025909,"lon":56.1936723,"hours":null,"location_details":null,"address":null,"url":null,"type":null,"city2":"Magtymguly","state2":"Balkan","country2":"Turkmenistan"},{"h3_12_4M":"8c2ccd4dc7a63ff","lat":38.6746478,"lon":56.9250337,"hours":null,"location_details":null,"address":null,"url":null,"type":null,"city2":"Baharly","state2":"Ahal","country2":"Turkmenistan"},{"h3_12_4M":"8c2ccdc10d84dff","lat":39.0061701,"lon":56.2535392,"hours":null,"location_details":null,"address":null,"url":null,"type":"pitlatrine","city2":"Serdar","state2":"Balkan","country2":"Turkmenistan"},{"h3_12_4M":"8c2ceab429467ff","lat":39.5203634,"lon":54.3700855,"hours":"Mo-Su 09:00-18:00","location_details":null,"address":null,"url":null,"type":null,"city2":"Balkanabat","state2":"Balkan","country2":"Turkmenistan"},{"h3_12_4M":"8c436c8090953ff","lat":37.5745978,"lon":61.8339643,"hours":"Mo-Su 08:00-18:00","location_details":null,"address":null,"url":null,"type":null,"city2":"Mary","state2":"Mary","country2":"Turkmenistan"}]